logic_superfence/__init__.py
logic_superfence/formatter.py
logic_superfence/plugin.py
logic_superfence/lib/bundle.js
logic_superfence/lib/bundle.js.map
logic_superfence-1.2.4.dist-info/licenses/COPYING
logic_superfence-1.2.4.dist-info/METADATA
logic_superfence-1.2.4.dist-info/WHEEL
logic_superfence-1.2.4.dist-info/entry_points.txt
logic_superfence-1.2.4.dist-info/top_level.txt
logic_superfence-1.2.4.dist-info/RECORD
