Metadata-Version: 2.4
Name: logic_superfence
Version: 1.2.4
Summary: A superfence pymarkdown extension to display Logic-Circuit-Simulator
Home-page: https://logic-superfence.gitlab.io
Author: Davy Cottet
License: GNU General Public License v3.0
Platform: Any
Classifier: Programming Language :: Python :: 3
Classifier: License :: OSI Approved :: GNU General Public License v3 (GPLv3)
License-File: COPYING
Requires-Dist: markdown
Requires-Dist: pymdown-extensions
Dynamic: author
Dynamic: classifier
Dynamic: home-page
Dynamic: license
Dynamic: license-file
Dynamic: platform
Dynamic: requires-dist
Dynamic: summary
